filebeat_delegate
test
